{
    "last_run": "2025-01-24 00:15:41",
    "status": "Success",
    "airports": {
        "PALMA DE MALLORCA": {
            "status": "Success",
            "message": "Data collected successfully",
            "last_update": "2025-01-24 00:15:41"
        },
        "GRAN CANARIA": {
            "status": "Success",
            "message": "Data collected successfully",
            "last_update": "2025-01-24 00:15:41"
        },
        "TENERIFE SUR": {
            "status": "Success",
            "message": "Data collected successfully",
            "last_update": "2025-01-24 00:15:41"
        },
        "TENERIFE NORTE-CIUDAD DE LA LAGUNA": {
            "status": "Success",
            "message": "Data collected successfully",
            "last_update": "2025-01-24 00:15:41"
        },
        "CÉSAR MANRIQUE-LANZAROTE": {
            "status": "Success",
            "message": "Data collected successfully",
            "last_update": "2025-01-24 00:15:41"
        },
        "FUERTEVENTURA": {
            "status": "Success",
            "message": "Data collected successfully",
            "last_update": "2025-01-24 00:15:41"
        },
        "MENORCA": {
            "status": "Success",
            "message": "Data collected successfully",
            "last_update": "2025-01-24 00:15:41"
        },
        "IBIZA": {
            "status": "Success",
            "message": "Data collected successfully",
            "last_update": "2025-01-24 00:15:41"
        },
        "MÁLAGA-COSTA DEL SOL": {
            "status": "Success",
            "message": "Data collected successfully",
            "last_update": "2025-01-24 00:15:41"
        },
        "SEVILLA": {
            "status": "Success",
            "message": "Data collected successfully",
            "last_update": "2025-01-24 00:15:41"
        },
        "JEREZ": {
            "status": "Error",
            "message": "Message: no such element: Unable to locate element: {\"method\":\"css selector\",\"selector\":\".listado\"}\n  (Session info: chrome=132.0.6834.83); For documentation on this error, please visit: https://www.selenium.dev/documentation/webdriver/troubleshooting/errors#no-such-element-exception\nStacktrace:\n#0 0x564973c6adca <unknown>\n#1 0x5649737613f0 <unknown>\n#2 0x5649737b110c <unknown>\n#3 0x5649737b1331 <unknown>\n#4 0x5649737f7154 <unknown>\n#5 0x5649737d5abd <unknown>\n#6 0x5649737f44b3 <unknown>\n#7 0x5649737d5833 <unknown>\n#8 0x5649737a25a0 <unknown>\n#9 0x5649737a3ece <unknown>\n#10 0x564973c34bdb <unknown>\n#11 0x564973c38b67 <unknown>\n#12 0x564973c203bc <unknown>\n#13 0x564973c39727 <unknown>\n#14 0x564973c0474f <unknown>\n#15 0x564973c59938 <unknown>\n#16 0x564973c59b00 <unknown>\n#17 0x564973c69c46 <unknown>\n#18 0x7f42c8a9ca94 <unknown>\n#19 0x7f42c8b29c3c <unknown>\n",
            "last_update": "2025-01-23 23:57:28"
        },
        "ALMERÍA": {
            "status": "Success",
            "message": "Data collected successfully",
            "last_update": "2025-01-24 00:15:41"
        },
        "JOSEP TARRADELLAS BARCELONA-EL PRAT": {
            "status": "Success",
            "message": "Data collected successfully",
            "last_update": "2025-01-24 00:15:41"
        },
        "GIRONA-COSTA BRAVA": {
            "status": "Success",
            "message": "Data collected successfully",
            "last_update": "2025-01-24 00:15:41"
        },
        "ALICANTE-ELCHE MIGUEL HERNÁNDEZ": {
            "status": "Success",
            "message": "Data collected successfully",
            "last_update": "2025-01-24 00:15:41"
        },
        "VALENCIA": {
            "status": "Success",
            "message": "Data collected successfully",
            "last_update": "2025-01-24 00:15:41"
        }
    }
}