{
    "last_run": "2024-12-14 11:35:00",
    "status": "Success",
    "airports": {
        "PALMA DE MALLORCA": {
            "status": "Error",
            "message": "Message: no such element: Unable to locate element: {\"method\":\"css selector\",\"selector\":\".listado\"}\n  (Session info: chrome=131.0.6778.108); For documentation on this error, please visit: https://www.selenium.dev/documentation/webdriver/troubleshooting/errors#no-such-element-exception\nStacktrace:\n#0 0x561b6b49131a <unknown>\n#1 0x561b6afa76e0 <unknown>\n#2 0x561b6aff63e6 <unknown>\n#3 0x561b6aff6681 <unknown>\n#4 0x561b6b03bb04 <unknown>\n#5 0x561b6b01a48d <unknown>\n#6 0x561b6b038ed7 <unknown>\n#7 0x561b6b01a203 <unknown>\n#8 0x561b6afe8cc0 <unknown>\n#9 0x561b6afe9c9e <unknown>\n#10 0x561b6b45ed0b <unknown>\n#11 0x561b6b462c92 <unknown>\n#12 0x561b6b44bb3c <unknown>\n#13 0x561b6b463807 <unknown>\n#14 0x561b6b4310df <unknown>\n#15 0x561b6b480578 <unknown>\n#16 0x561b6b480740 <unknown>\n#17 0x561b6b490196 <unknown>\n#18 0x7f301969ca94 <unknown>\n#19 0x7f3019729c3c <unknown>\n",
            "last_update": "2024-12-14 11:16:10"
        },
        "GRAN CANARIA": {
            "status": "Success",
            "message": "Data collected successfully",
            "last_update": "2024-12-14 11:35:00"
        },
        "TENERIFE SUR": {
            "status": "Success",
            "message": "Data collected successfully",
            "last_update": "2024-12-14 11:35:00"
        },
        "TENERIFE NORTE-CIUDAD DE LA LAGUNA": {
            "status": "Success",
            "message": "Data collected successfully",
            "last_update": "2024-12-14 11:35:00"
        },
        "CÉSAR MANRIQUE-LANZAROTE": {
            "status": "Success",
            "message": "Data collected successfully",
            "last_update": "2024-12-14 11:35:00"
        },
        "FUERTEVENTURA": {
            "status": "Success",
            "message": "Data collected successfully",
            "last_update": "2024-12-14 11:35:00"
        },
        "MENORCA": {
            "status": "Success",
            "message": "Data collected successfully",
            "last_update": "2024-12-14 11:35:00"
        },
        "IBIZA": {
            "status": "Success",
            "message": "Data collected successfully",
            "last_update": "2024-12-14 11:35:00"
        },
        "MÁLAGA-COSTA DEL SOL": {
            "status": "Success",
            "message": "Data collected successfully",
            "last_update": "2024-12-14 11:35:00"
        },
        "SEVILLA": {
            "status": "Success",
            "message": "Data collected successfully",
            "last_update": "2024-12-14 11:35:00"
        },
        "JEREZ": {
            "status": "Success",
            "message": "Data collected successfully",
            "last_update": "2024-12-14 11:35:00"
        },
        "ALMERÍA": {
            "status": "Success",
            "message": "Data collected successfully",
            "last_update": "2024-12-14 11:35:00"
        },
        "JOSEP TARRADELLAS BARCELONA-EL PRAT": {
            "status": "Success",
            "message": "Data collected successfully",
            "last_update": "2024-12-14 11:35:00"
        },
        "GIRONA-COSTA BRAVA": {
            "status": "Success",
            "message": "Data collected successfully",
            "last_update": "2024-12-14 11:35:00"
        },
        "ALICANTE-ELCHE MIGUEL HERNÁNDEZ": {
            "status": "Success",
            "message": "Data collected successfully",
            "last_update": "2024-12-14 11:35:00"
        },
        "VALENCIA": {
            "status": "Success",
            "message": "Data collected successfully",
            "last_update": "2024-12-14 11:35:00"
        }
    }
}