{
    "last_run": "2025-01-01 13:39:30",
    "status": "Success",
    "airports": {
        "PALMA DE MALLORCA": {
            "status": "Success",
            "message": "Data collected successfully",
            "last_update": "2025-01-01 13:39:30"
        },
        "GRAN CANARIA": {
            "status": "Success",
            "message": "Data collected successfully",
            "last_update": "2025-01-01 13:39:30"
        },
        "TENERIFE SUR": {
            "status": "Success",
            "message": "Data collected successfully",
            "last_update": "2025-01-01 13:39:30"
        },
        "TENERIFE NORTE-CIUDAD DE LA LAGUNA": {
            "status": "Success",
            "message": "Data collected successfully",
            "last_update": "2025-01-01 13:39:30"
        },
        "CÉSAR MANRIQUE-LANZAROTE": {
            "status": "Success",
            "message": "Data collected successfully",
            "last_update": "2025-01-01 13:39:30"
        },
        "FUERTEVENTURA": {
            "status": "Success",
            "message": "Data collected successfully",
            "last_update": "2025-01-01 13:39:30"
        },
        "MENORCA": {
            "status": "Success",
            "message": "Data collected successfully",
            "last_update": "2025-01-01 13:39:30"
        },
        "IBIZA": {
            "status": "Success",
            "message": "Data collected successfully",
            "last_update": "2025-01-01 13:39:30"
        },
        "MÁLAGA-COSTA DEL SOL": {
            "status": "Success",
            "message": "Data collected successfully",
            "last_update": "2025-01-01 13:39:30"
        },
        "SEVILLA": {
            "status": "Success",
            "message": "Data collected successfully",
            "last_update": "2025-01-01 13:39:30"
        },
        "JEREZ": {
            "status": "Success",
            "message": "Data collected successfully",
            "last_update": "2025-01-01 13:39:30"
        },
        "ALMERÍA": {
            "status": "Success",
            "message": "Data collected successfully",
            "last_update": "2025-01-01 13:39:30"
        },
        "JOSEP TARRADELLAS BARCELONA-EL PRAT": {
            "status": "Success",
            "message": "Data collected successfully",
            "last_update": "2025-01-01 13:39:30"
        },
        "GIRONA-COSTA BRAVA": {
            "status": "Error",
            "message": "Message: no such element: Unable to locate element: {\"method\":\"css selector\",\"selector\":\".listado\"}\n  (Session info: chrome=131.0.6778.139); For documentation on this error, please visit: https://www.selenium.dev/documentation/webdriver/troubleshooting/errors#no-such-element-exception\nStacktrace:\n#0 0x56211e9008fa <unknown>\n#1 0x56211e411d20 <unknown>\n#2 0x56211e460a66 <unknown>\n#3 0x56211e460d01 <unknown>\n#4 0x56211e4a6184 <unknown>\n#5 0x56211e484b1d <unknown>\n#6 0x56211e4a3560 <unknown>\n#7 0x56211e484893 <unknown>\n#8 0x56211e45330d <unknown>\n#9 0x56211e45432e <unknown>\n#10 0x56211e8cd00b <unknown>\n#11 0x56211e8d0f97 <unknown>\n#12 0x56211e8b971c <unknown>\n#13 0x56211e8d1b17 <unknown>\n#14 0x56211e89e6cf <unknown>\n#15 0x56211e8ef6b8 <unknown>\n#16 0x56211e8ef880 <unknown>\n#17 0x56211e8ff776 <unknown>\n#18 0x7f1fc0c9ca94 <unknown>\n#19 0x7f1fc0d29c3c <unknown>\n",
            "last_update": "2025-01-01 12:59:15"
        },
        "ALICANTE-ELCHE MIGUEL HERNÁNDEZ": {
            "status": "Success",
            "message": "Data collected successfully",
            "last_update": "2025-01-01 13:39:30"
        },
        "VALENCIA": {
            "status": "Success",
            "message": "Data collected successfully",
            "last_update": "2025-01-01 13:39:30"
        }
    }
}