{
    "last_run": "2024-12-24 21:41:06",
    "status": "Success",
    "airports": {
        "PALMA DE MALLORCA": {
            "status": "Error",
            "message": "Message: no such element: Unable to locate element: {\"method\":\"css selector\",\"selector\":\".listado\"}\n  (Session info: chrome=131.0.6778.139); For documentation on this error, please visit: https://www.selenium.dev/documentation/webdriver/troubleshooting/errors#no-such-element-exception\nStacktrace:\n#0 0x55c3b4d488fa <unknown>\n#1 0x55c3b4859d20 <unknown>\n#2 0x55c3b48a8a66 <unknown>\n#3 0x55c3b48a8d01 <unknown>\n#4 0x55c3b48ee184 <unknown>\n#5 0x55c3b48ccb1d <unknown>\n#6 0x55c3b48eb560 <unknown>\n#7 0x55c3b48cc893 <unknown>\n#8 0x55c3b489b30d <unknown>\n#9 0x55c3b489c32e <unknown>\n#10 0x55c3b4d1500b <unknown>\n#11 0x55c3b4d18f97 <unknown>\n#12 0x55c3b4d0171c <unknown>\n#13 0x55c3b4d19b17 <unknown>\n#14 0x55c3b4ce66cf <unknown>\n#15 0x55c3b4d376b8 <unknown>\n#16 0x55c3b4d37880 <unknown>\n#17 0x55c3b4d47776 <unknown>\n#18 0x7fe1ae29ca94 <unknown>\n#19 0x7fe1ae329c3c <unknown>\n",
            "last_update": "2024-12-24 21:19:06"
        },
        "GRAN CANARIA": {
            "status": "Success",
            "message": "Data collected successfully",
            "last_update": "2024-12-24 21:41:06"
        },
        "TENERIFE SUR": {
            "status": "Success",
            "message": "Data collected successfully",
            "last_update": "2024-12-24 21:41:06"
        },
        "TENERIFE NORTE-CIUDAD DE LA LAGUNA": {
            "status": "Success",
            "message": "Data collected successfully",
            "last_update": "2024-12-24 21:41:06"
        },
        "CÉSAR MANRIQUE-LANZAROTE": {
            "status": "Success",
            "message": "Data collected successfully",
            "last_update": "2024-12-24 21:41:06"
        },
        "FUERTEVENTURA": {
            "status": "Error",
            "message": "Message: no such element: Unable to locate element: {\"method\":\"css selector\",\"selector\":\".listado\"}\n  (Session info: chrome=131.0.6778.139); For documentation on this error, please visit: https://www.selenium.dev/documentation/webdriver/troubleshooting/errors#no-such-element-exception\nStacktrace:\n#0 0x55c3b4d488fa <unknown>\n#1 0x55c3b4859d20 <unknown>\n#2 0x55c3b48a8a66 <unknown>\n#3 0x55c3b48a8d01 <unknown>\n#4 0x55c3b48ee184 <unknown>\n#5 0x55c3b48ccb1d <unknown>\n#6 0x55c3b48eb560 <unknown>\n#7 0x55c3b48cc893 <unknown>\n#8 0x55c3b489b30d <unknown>\n#9 0x55c3b489c32e <unknown>\n#10 0x55c3b4d1500b <unknown>\n#11 0x55c3b4d18f97 <unknown>\n#12 0x55c3b4d0171c <unknown>\n#13 0x55c3b4d19b17 <unknown>\n#14 0x55c3b4ce66cf <unknown>\n#15 0x55c3b4d376b8 <unknown>\n#16 0x55c3b4d37880 <unknown>\n#17 0x55c3b4d47776 <unknown>\n#18 0x7fe1ae29ca94 <unknown>\n#19 0x7fe1ae329c3c <unknown>\n",
            "last_update": "2024-12-24 20:58:08"
        },
        "MENORCA": {
            "status": "Success",
            "message": "Data collected successfully",
            "last_update": "2024-12-24 21:41:06"
        },
        "IBIZA": {
            "status": "Success",
            "message": "Data collected successfully",
            "last_update": "2024-12-24 21:41:06"
        },
        "MÁLAGA-COSTA DEL SOL": {
            "status": "Success",
            "message": "Data collected successfully",
            "last_update": "2024-12-24 21:41:06"
        },
        "SEVILLA": {
            "status": "Error",
            "message": "Message: no such element: Unable to locate element: {\"method\":\"css selector\",\"selector\":\".listado\"}\n  (Session info: chrome=131.0.6778.139); For documentation on this error, please visit: https://www.selenium.dev/documentation/webdriver/troubleshooting/errors#no-such-element-exception\nStacktrace:\n#0 0x55c3b4d488fa <unknown>\n#1 0x55c3b4859d20 <unknown>\n#2 0x55c3b48a8a66 <unknown>\n#3 0x55c3b48a8d01 <unknown>\n#4 0x55c3b48ee184 <unknown>\n#5 0x55c3b48ccb1d <unknown>\n#6 0x55c3b48eb560 <unknown>\n#7 0x55c3b48cc893 <unknown>\n#8 0x55c3b489b30d <unknown>\n#9 0x55c3b489c32e <unknown>\n#10 0x55c3b4d1500b <unknown>\n#11 0x55c3b4d18f97 <unknown>\n#12 0x55c3b4d0171c <unknown>\n#13 0x55c3b4d19b17 <unknown>\n#14 0x55c3b4ce66cf <unknown>\n#15 0x55c3b4d376b8 <unknown>\n#16 0x55c3b4d37880 <unknown>\n#17 0x55c3b4d47776 <unknown>\n#18 0x7fe1ae29ca94 <unknown>\n#19 0x7fe1ae329c3c <unknown>\n",
            "last_update": "2024-12-24 21:31:00"
        },
        "JEREZ": {
            "status": "Success",
            "message": "Data collected successfully",
            "last_update": "2024-12-24 21:41:06"
        },
        "ALMERÍA": {
            "status": "Success",
            "message": "Data collected successfully",
            "last_update": "2024-12-24 21:41:06"
        },
        "JOSEP TARRADELLAS BARCELONA-EL PRAT": {
            "status": "Success",
            "message": "Data collected successfully",
            "last_update": "2024-12-24 21:41:06"
        },
        "GIRONA-COSTA BRAVA": {
            "status": "Success",
            "message": "Data collected successfully",
            "last_update": "2024-12-24 21:41:06"
        },
        "ALICANTE-ELCHE MIGUEL HERNÁNDEZ": {
            "status": "Success",
            "message": "Data collected successfully",
            "last_update": "2024-12-24 21:41:06"
        },
        "VALENCIA": {
            "status": "Error",
            "message": "Message: no such element: Unable to locate element: {\"method\":\"css selector\",\"selector\":\".listado\"}\n  (Session info: chrome=131.0.6778.139); For documentation on this error, please visit: https://www.selenium.dev/documentation/webdriver/troubleshooting/errors#no-such-element-exception\nStacktrace:\n#0 0x55c3b4d488fa <unknown>\n#1 0x55c3b4859d20 <unknown>\n#2 0x55c3b48a8a66 <unknown>\n#3 0x55c3b48a8d01 <unknown>\n#4 0x55c3b48ee184 <unknown>\n#5 0x55c3b48ccb1d <unknown>\n#6 0x55c3b48eb560 <unknown>\n#7 0x55c3b48cc893 <unknown>\n#8 0x55c3b489b30d <unknown>\n#9 0x55c3b489c32e <unknown>\n#10 0x55c3b4d1500b <unknown>\n#11 0x55c3b4d18f97 <unknown>\n#12 0x55c3b4d0171c <unknown>\n#13 0x55c3b4d19b17 <unknown>\n#14 0x55c3b4ce66cf <unknown>\n#15 0x55c3b4d376b8 <unknown>\n#16 0x55c3b4d37880 <unknown>\n#17 0x55c3b4d47776 <unknown>\n#18 0x7fe1ae29ca94 <unknown>\n#19 0x7fe1ae329c3c <unknown>\n",
            "last_update": "2024-12-24 21:31:00"
        }
    }
}