{
    "last_run": "2024-12-09 19:00:21",
    "status": "Success",
    "airports": {
        "PALMA DE MALLORCA": {
            "status": "Success",
            "message": "Data collected successfully",
            "last_update": "2024-12-09 19:00:21"
        },
        "GRAN CANARIA": {
            "status": "Success",
            "message": "Data collected successfully",
            "last_update": "2024-12-09 19:00:21"
        },
        "TENERIFE SUR": {
            "status": "Success",
            "message": "Data collected successfully",
            "last_update": "2024-12-09 19:00:21"
        },
        "TENERIFE NORTE-CIUDAD DE LA LAGUNA": {
            "status": "Success",
            "message": "Data collected successfully",
            "last_update": "2024-12-09 19:00:21"
        },
        "CÉSAR MANRIQUE-LANZAROTE": {
            "status": "Success",
            "message": "Data collected successfully",
            "last_update": "2024-12-09 19:00:21"
        },
        "FUERTEVENTURA": {
            "status": "Success",
            "message": "Data collected successfully",
            "last_update": "2024-12-09 19:00:21"
        },
        "MENORCA": {
            "status": "Success",
            "message": "Data collected successfully",
            "last_update": "2024-12-09 19:00:21"
        },
        "IBIZA": {
            "status": "Success",
            "message": "Data collected successfully",
            "last_update": "2024-12-09 19:00:21"
        },
        "MÁLAGA-COSTA DEL SOL": {
            "status": "Success",
            "message": "Data collected successfully",
            "last_update": "2024-12-09 19:00:21"
        },
        "SEVILLA": {
            "status": "Success",
            "message": "Data collected successfully",
            "last_update": "2024-12-09 19:00:21"
        },
        "JEREZ": {
            "status": "Error",
            "message": "TimeoutException",
            "last_update": "2024-12-09 18:52:13"
        },
        "ALMERÍA": {
            "status": "Success",
            "message": "Data collected successfully",
            "last_update": "2024-12-09 19:00:21"
        },
        "JOSEP TARRADELLAS BARCELONA-EL PRAT": {
            "status": "Success",
            "message": "Data collected successfully",
            "last_update": "2024-12-09 19:00:21"
        },
        "GIRONA-COSTA BRAVA": {
            "status": "Error",
            "message": "TimeoutException"
        },
        "ALICANTE-ELCHE MIGUEL HERNÁNDEZ": {
            "status": "Success",
            "message": "Data collected successfully",
            "last_update": "2024-12-09 19:00:21"
        },
        "VALENCIA": {
            "status": "Error",
            "message": "TimeoutException",
            "last_update": "2024-12-09 18:52:13"
        }
    }
}